django_sqlite_backup/__init__.py
django_sqlite_backup/apps.py
django_sqlite_backup/aws.py
django_sqlite_backup/backup.py
django_sqlite_backup/restore.py
django_sqlite_backup/urls.py
django_sqlite_backup/views.py
django_sqlite_backup/management/commands/__init__.py
django_sqlite_backup/management/commands/backup.py
django_sqlite_backup/management/commands/restore.py
django_sqlite_backup-0.2.0.dist-info/licenses/LICENSE
django_sqlite_backup-0.2.0.dist-info/METADATA
django_sqlite_backup-0.2.0.dist-info/WHEEL
django_sqlite_backup-0.2.0.dist-info/top_level.txt
django_sqlite_backup-0.2.0.dist-info/RECORD
