Metadata-Version: 2.4
Name: django-sqlite-backup
Version: 0.2.0
Summary: A Django app to easily backup your sqlite database through an endpoint.
Author-email: Ferran Jovell <ferran.jovell+gh@gmail.com>
License: MIT License
Project-URL: homepage, https://github.com/mrswats/django-sqlite-backup
Project-URL: Bug Tracker, https://github.com/mrswats/django-sqlite-backup/issues
Keywords: django
Classifier: Intended Audience :: Developers
Classifier: License :: OSI Approved :: MIT License
Classifier: Programming Language :: Python :: 3.8
Classifier: Programming Language :: Python :: 3.9
Classifier: Programming Language :: Python :: 3.10
Classifier: Programming Language :: Python :: 3.11
Classifier: Operating System :: OS Independent
Classifier: Topic :: Software Development :: Libraries
Classifier: Environment :: Web Environment
Classifier: Framework :: Django
Requires-Python: >=3.9
License-File: LICENSE
Requires-Dist: Django
Requires-Dist: asgiref
Provides-Extra: aws
Requires-Dist: boto3; extra == "aws"
Provides-Extra: test
Requires-Dist: boto3; extra == "test"
Requires-Dist: coverage; extra == "test"
Requires-Dist: moto; extra == "test"
Requires-Dist: pytest; extra == "test"
Requires-Dist: pytest-django; extra == "test"
Requires-Dist: time-machine; extra == "test"
Dynamic: license-file
